taskiq_aio_sqs/__init__.py
taskiq_aio_sqs/constants.py
taskiq_aio_sqs/exceptions.py
taskiq_aio_sqs/py.typed
taskiq_aio_sqs/s3_backend.py
taskiq_aio_sqs/sqs_broker.py
taskiq_aio_sqs-1.1.0.dist-info/METADATA
taskiq_aio_sqs-1.1.0.dist-info/WHEEL
taskiq_aio_sqs-1.1.0.dist-info/licenses/LICENSE
taskiq_aio_sqs-1.1.0.dist-info/RECORD
