Metadata-Version: 2.4
Name: taskiq-aio-sqs
Version: 1.1.0
Summary: SQS/S3 Broker for TaskIQ using Aiobotocore
Project-URL: source, https://github.com/vonsteer/taskiq-aio-sqs
License: MIT License
License-File: LICENSE
Keywords: aiobotocore,aws,broker,queue,s3,sqs,taskiq,taskiq-broker
Classifier: Development Status :: 5 - Production/Stable
Classifier: Framework :: AsyncIO
Classifier: Intended Audience :: Developers
Classifier: Intended Audience :: Information Technology
Classifier: License :: OSI Approved :: MIT License
Classifier: Natural Language :: English
Classifier: Operating System :: OS Independent
Classifier: Programming Language :: Python
Classifier: Programming Language :: Python :: 3
Classifier: Programming Language :: Python :: 3 :: Only
Classifier: Programming Language :: Python :: 3.10
Classifier: Programming Language :: Python :: 3.11
Classifier: Programming Language :: Python :: 3.12
Classifier: Programming Language :: Python :: 3.13
Classifier: Programming Language :: Python :: 3.14
Classifier: Topic :: Software Development
Classifier: Topic :: Software Development :: Libraries
Classifier: Topic :: Software Development :: Libraries :: Python Modules
Classifier: Topic :: System :: Networking
Classifier: Typing :: Typed
Requires-Python: >=3.10
Requires-Dist: aiobotocore>=2.23.1
Requires-Dist: annotated-types~=0.7.0
Requires-Dist: pydantic<=3.0,>=1.0
Requires-Dist: taskiq[orjson]<1,>=0.11.12
